setup.py
pyramid_eplasty/__init__.py
pyramid_eplasty/collection.py
pyramid_eplasty/data_manager.py
pyramid_eplasty/tween.py
pyramid_eplasty.egg-info/PKG-INFO
pyramid_eplasty.egg-info/SOURCES.txt
pyramid_eplasty.egg-info/dependency_links.txt
pyramid_eplasty.egg-info/requires.txt
pyramid_eplasty.egg-info/top_level.txt