Metadata-Version: 1.1
Name: pyramid_eplasty
Version: 0.0.3
Summary: Include this in a pyramid project to get elephantoplasty support
Home-page: http://github.com/zefciu/Elephantoplasty
Author: Szymon Pyżalski
Author-email: zefciu <szymon@pythonista.net>
License: BSD
Keywords: orm postgresql psql pg persistence sql relational database
Platform: UNKNOWN
Classifier: Development Status :: 3 - Alpha
Classifier: Intended Audience :: Developers
Classifier: License :: OSI Approved :: BSD License
Classifier: Programming Language :: Python :: 2
Classifier: Programming Language :: Python :: 2.6
Classifier: Programming Language :: Python :: 2.7
Classifier: Programming Language :: Python :: 3
Classifier: Programming Language :: Python :: 3.2
Classifier: Topic :: Database :: Front-Ends
